finance_sdk/__init__.py
finance_sdk/admin.py
finance_sdk/apps.py
finance_sdk/enums.py
finance_sdk/tests.py
finance_sdk/utils.py
finance_sdk/migrations/__init__.py
finance_sdk/models/__init__.py
finance_sdk/models/accounts.py
finance_sdk/models/bank.py
finance_sdk/models/category.py
finance_sdk/models/entry.py
finance_sdk/models/payment.py
finance_sdk/models/receipts.py
finance_sdk/serializers/__init__.py
finance_sdk/serializers/accounts.py
finance_sdk/serializers/bank.py
finance_sdk/serializers/category.py
finance_sdk/serializers/entry.py
finance_sdk/serializers/payments.py
finance_sdk/services/__init__.py
finance_sdk/services/entriesService.py
finance_sdk/views/__init__.py
finance_sdk/views/account.py
finance_sdk/views/bank.py
finance_sdk/views/category.py
finance_sdk/views/entry.py
finance_sdk/views/payment.py
finance_sdk-1.0.12.dist-info/METADATA
finance_sdk-1.0.12.dist-info/WHEEL
finance_sdk-1.0.12.dist-info/top_level.txt
finance_sdk-1.0.12.dist-info/RECORD
